{
  "piece": 76,
  "duration_ms": 85089,
  "cues": [
    {
      "time_ms": 26935,
      "end_ms": 27353,
      "line": 119,
      "target": "envelope",
      "context": "illegible \u2014 look at the envelope function governing opacity, which borrows"
    },
    {
      "time_ms": 32543,
      "end_ms": 33007,
      "line": 121,
      "target": "attack",
      "context": "borrows an ADSR sound-envelope structure, attack into decay into sustain, so"
    },
    {
      "time_ms": 33530,
      "end_ms": 33924,
      "line": 122,
      "target": "decay",
      "context": "ADSR sound-envelope structure, attack into decay into sustain, so every line"
    },
    {
      "time_ms": 45000,
      "end_ms": 46370,
      "line": 155,
      "target": "traceToSubstrate",
      "context": "it doesn't vanish \u2014 in traceToSubstrate, it gets copied into a"
    },
    {
      "time_ms": 49505,
      "end_ms": 53348,
      "line": 154,
      "target": "CHANGE 3: Add trace to substrate - the unchosen reabsorbed into field",
      "context": "a separate blurred layer called substrate, \"the unchosen reabsorbed into field,\" still glowing underneath at low"
    }
  ]
}